{
    "vocab_data": {
        "change": {
            "sentence": "The product is undergoing a change in order to improve it.",
            "pos": "Động từ | Danh từ",
            "vn_meaning": "thay đổi",
            "last_studied": "2026-04-08 23:56",
            "study_count": 1,
            "custom_sentence": ""
        },
        "adult": {
            "sentence": "an adult human, animal, or plant",
            "pos": "Động từ | Tính từ | Danh từ",
            "vn_meaning": "người lớn",
            "last_studied": "2026-04-08 23:57",
            "study_count": 1,
            "custom_sentence": ""
        },
        "have": {
            "sentence": "I have a house and a car.",
            "pos": "Động từ | Danh từ",
            "vn_meaning": "có",
            "last_studied": "2026-04-08 23:57",
            "study_count": 1,
            "custom_sentence": ""
        },
        "about": {
            "sentence": "After my bout with Guillan-Barre Syndrome, it took me 6 months to be up and about again.",
            "pos": "Giới từ | Tính từ | Trạng từ",
            "vn_meaning": "Về",
            "last_studied": "2026-04-08 23:52",
            "study_count": 1,
            "custom_sentence": ""
        }
    },
    "daily_study_tracker": {
        "2026-04-08": [
            "attend",
            "he",
            "helo"
        ]
    },
    "daily_tracker": {
        "2026-04-08": [
            "he",
            "helo",
            "attend",
            "smile",
            "accommodate",
            "blue",
            "hello",
            "change",
            "adult",
            "have",
            "about"
        ],
        "accommodate": [
            "2026-04-08"
        ],
        "attend": [
            "2026-04-08"
        ],
        "smile": [
            "2026-04-08"
        ],
        "hello": [
            "2026-04-08"
        ],
        "blue": [
            "2026-04-08"
        ]
    }
}